doc/conf.py
simpleadb/__init__.py
simpleadb/adbcmds.py
simpleadb/adbdevice.py
simpleadb/adbprocess.py
simpleadb/adbserver.py
simpleadb/utils.py
simpleadb-0.5.4.dist-info/licenses/LICENSE
simpleadb-0.5.4.dist-info/METADATA
simpleadb-0.5.4.dist-info/WHEEL
simpleadb-0.5.4.dist-info/top_level.txt
simpleadb-0.5.4.dist-info/RECORD
