Metadata-Version: 2.4
Name: simpleadb
Version: 0.5.4
Summary: Python wrapper for adb protocol.
Author-email: Michal Kielan <michalkielan@protonmail.com>
License-Expression: GPL-3.0-only
Project-URL: Homepage, https://github.com/michalkielan/simple-adb
Requires-Python: >=3.9
License-File: LICENSE
Dynamic: license-file
